highcharts_maps/__init__.py
highcharts_maps/__version__.py
highcharts_maps/ai.py
highcharts_maps/chart.py
highcharts_maps/constants.py
highcharts_maps/decorators.py
highcharts_maps/errors.py
highcharts_maps/headless_export.py
highcharts_maps/highcharts.py
highcharts_maps/js_literal_functions.py
highcharts_maps/metaclasses.py
highcharts_maps/utility_functions.py
highcharts_maps/global_options/__init__.py
highcharts_maps/global_options/shared_options.py
highcharts_maps/global_options/language/__init__.py
highcharts_maps/global_options/language/export_data.py
highcharts_maps/global_options/language/navigation.py
highcharts_maps/global_options/language/accessibility/__init__.py
highcharts_maps/global_options/language/accessibility/announce_new_data.py
highcharts_maps/global_options/language/accessibility/axis.py
highcharts_maps/global_options/language/accessibility/chart_types.py
highcharts_maps/global_options/language/accessibility/exporting.py
highcharts_maps/global_options/language/accessibility/legend.py
highcharts_maps/global_options/language/accessibility/navigator.py
highcharts_maps/global_options/language/accessibility/range_selector.py
highcharts_maps/global_options/language/accessibility/screen_reader_section.py
highcharts_maps/global_options/language/accessibility/series.py
highcharts_maps/global_options/language/accessibility/sonification.py
highcharts_maps/global_options/language/accessibility/table.py
highcharts_maps/global_options/language/accessibility/zoom.py
highcharts_maps/options/__init__.py
highcharts_maps/options/boost.py
highcharts_maps/options/caption.py
highcharts_maps/options/credits.py
highcharts_maps/options/data.py
highcharts_maps/options/defs.py
highcharts_maps/options/drilldown.py
highcharts_maps/options/loading.py
highcharts_maps/options/map_navigation.py
highcharts_maps/options/responsive.py
highcharts_maps/options/subtitle.py
highcharts_maps/options/time.py
highcharts_maps/options/title.py
highcharts_maps/options/tooltips.py
highcharts_maps-1.7.1.dist-info/METADATA
highcharts_maps-1.7.1.dist-info/WHEEL
highcharts_maps-1.7.1.dist-info/licenses/LICENSE
highcharts_maps-1.7.1.dist-info/RECORD
